powerline_swissarmyknife/__init__.py
powerline_swissarmyknife/execute.py
powerline_swissarmyknife-1.0.0.dist-info/LICENSE
powerline_swissarmyknife-1.0.0.dist-info/METADATA
powerline_swissarmyknife-1.0.0.dist-info/WHEEL
powerline_swissarmyknife-1.0.0.dist-info/top_level.txt
powerline_swissarmyknife-1.0.0.dist-info/RECORD
