Metadata-Version: 2.1
Name: powerline-swissarmyknife
Version: 1.0.0
Summary: A Powerline segment.This segment shows the execution of complex command line defined by user.
Home-page: https://github.com/mdtrooper/powerline_swissarmyknife
Author: Miguel de Dios Matias
Author-email: tres.14159@gmail.com
License: GPLv3+
Platform: any
Classifier: Programming Language :: Python :: 3
Classifier: License :: OSI Approved :: GNU General Public License v3 or later (GPLv3+)
Classifier: Operating System :: OS Independent
Classifier: Environment :: Console
Requires-Python: >=3.7
